dnres/__init__.py
dnres-0.2.0.dist-info/LICENSE
dnres-0.2.0.dist-info/METADATA
dnres-0.2.0.dist-info/WHEEL
dnres-0.2.0.dist-info/top_level.txt
dnres-0.2.0.dist-info/RECORD
