Metadata-Version: 2.1
Name: dnres
Version: 0.2.0
Summary: Managing and sharing data and results of analysis.
Home-page: UNKNOWN
Author: Dimitrios Kioroglou
Author-email: <d.kioroglou@hotmail.com>
License: UNKNOWN
Keywords: python,data analysis,bioinformatics,reporting,analysis results
Platform: UNKNOWN
Classifier: Development Status :: 1 - Planning
Classifier: Intended Audience :: Science/Research
Classifier: Programming Language :: Python :: 3
Classifier: Operating System :: Unix
Classifier: Operating System :: MacOS :: MacOS X
Classifier: Operating System :: Microsoft :: Windows
License-File: LICENSE
Requires-Dist: rich
